{"character":"main.sergey","sheet":"enemies.seahorse","headIdx":3,"class":"???????","comboCount":6,"stats":{"hp":{"base":0,"increase":0,"variance":0.1},"attack":{"base":0,"increase":0,"variance":0.9},"defense":{"base":0,"increase":0,"variance":0.5},"focus":{"base":0,"increase":0,"variance":0.3}},"autoequip":[{"level":3,"HEAD":23,"LEFT_ARM":24,"RIGHT_ARM":24,"TORSO":26,"FEET":25},{"level":6,"HEAD":31,"LEFT_ARM":29,"RIGHT_ARM":29,"TORSO":30,"FEET":32},{"level":10,"HEAD":31,"LEFT_ARM":56,"RIGHT_ARM":29,"TORSO":41,"FEET":45},{"level":13,"HEAD":50,"LEFT_ARM":56,"RIGHT_ARM":57,"TORSO":48,"FEET":45},{"level":16,"HEAD":118,"LEFT_ARM":113,"RIGHT_ARM":57,"TORSO":122,"FEET":121},{"level":20,"HEAD":117,"LEFT_ARM":114,"RIGHT_ARM":84,"TORSO":125,"FEET":46},{"level":23,"HEAD":208,"LEFT_ARM":209,"RIGHT_ARM":38,"TORSO":210,"FEET":46},{"level":25,"HEAD":204,"LEFT_ARM":205,"RIGHT_ARM":38,"TORSO":206,"FEET":46},{"level":28,"HEAD":214,"LEFT_ARM":221,"RIGHT_ARM":38,"TORSO":216,"FEET":218}],"DOCTYPE":"PLAYER","proxies":{},"actions":{"BASE":{},"NEUTRAL":{},"HEAT":{},"COLD":{},"SHOCK":{},"WAVE":{}}}