{"DOCTYPE":"MULTI_DIR_ANIMATION","namedSheets":{"move":{"src":"media\/entity\/enemy\/sandshark.png","offX":0,"offY":0,"width":64,"height":48},"move2":{"src":"media\/entity\/enemy\/sandshark.png","xCount":8,"offX":0,"offY":144,"width":64,"height":48},"weak":{"src":"media\/entity\/enemy\/sandshark.png","offX":512,"offY":144,"width":64,"height":48}},"shapeType":"Z_EXPAND","gfxOffset":{"x":0,"y":8},"wallY":0.33,"dirs":"6","SUB":[{"sheet":"move","flipX":[0,0,0,1,1,1],"tileOffsets":[0,10,20,20,10,0],"SUB":[{"name":"idle","time":0.133,"repeat":true,"frames":[0,1,2,3]},{"name":"diveDown","time":0.2,"repeat":false,"frames":[4,5,6]},{"name":"hidden","time":0.2,"repeat":false,"frames":[]},{"name":"riseUp","time":0.2,"repeat":false,"frames":[6,5]},{"name":"jump","time":0.1333,"repeat":true,"frames":[7]},{"name":"topShake","time":0.05,"repeat":true,"frames":[8,8],"framesGfxOffset":[1,0,0,0]},{"name":"fall","time":0.1,"repeat":false,"frames":[8,9]}]},{"sheet":"move2","flipX":[0,0,0,1,1,1],"tileOffsets":[0,8,16,16,8,0],"SUB":[{"name":"jumpStart","time":0.05,"repeat":false,"frames":[0,1,2,3]},{"name":"jumpEnd","time":0.05,"repeat":false,"frames":[4,5,6,7]}]},{"sheet":"weak","dirs":"2","flipX":[0,1],"tileOffsets":[0,0],"SUB":[{"name":"weak","time":0.066,"repeat":true,"frames":[0,1,2,3]}]}]}